librecubo_reference/__init__.py
librecubo_reference/foo.py
librecubo_reference-0.0.1.dist-info/LICENSE
librecubo_reference-0.0.1.dist-info/METADATA
librecubo_reference-0.0.1.dist-info/WHEEL
librecubo_reference-0.0.1.dist-info/RECORD
