Metadata-Version: 2.1
Name: librecubo_reference
Version: 0.0.1
Summary: This is a template repository for Python projects that use Poetry for their dependency management.
Home-page: https://github.com/JulioContrerasH/librecubo-reference
Author: Julio Contreras
Author-email: fjulio.contreras1@unmsm.edu.pe
Requires-Python: >=3.9,<4.0
Classifier: Programming Language :: Python :: 3
Classifier: Programming Language :: Python :: 3.9
Classifier: Programming Language :: Python :: 3.10
Classifier: Programming Language :: Python :: 3.11
Classifier: Programming Language :: Python :: 3.12
Requires-Dist: cubo (>=2023.7.2,<2024.0.0)
Requires-Dist: librecubo-clouds (>=0.0.1,<0.0.2)
Project-URL: Documentation, https://JulioContrerasH.github.io/librecubo-reference/
Project-URL: Repository, https://github.com/JulioContrerasH/librecubo-reference
